MANIFEST.in
setup.py
bin/sqlcrush
sqlcrush/__init__.py
sqlcrush/database.py
sqlcrush/saved_databases
sqlcrush/user_input.py
sqlcrush.egg-info/PKG-INFO
sqlcrush.egg-info/SOURCES.txt
sqlcrush.egg-info/dependency_links.txt
sqlcrush.egg-info/requires.txt
sqlcrush.egg-info/top_level.txt