Metadata-Version: 1.0
Name: sqlcrush
Version: 0.1.5
Summary: console based database editor
Home-page: http://github.com/coffeeandscripts/sqlcrush
Author: coffeeandscripts
Author-email: ersari94@gmail.com
License: GNU
Platform: UNKNOWN
